setup.py
excel_export/__init__.py
excel_export/cli.py
excel_export/export.py
excel_export/extract.py
excel_export.egg-info/.gitignore
excel_export.egg-info/PKG-INFO
excel_export.egg-info/SOURCES.txt
excel_export.egg-info/dependency_links.txt
excel_export.egg-info/entry_points.txt
excel_export.egg-info/requires.txt
excel_export.egg-info/top_level.txt