Metadata-Version: 1.0
Name: excel-export
Version: 0.4.0
Summary: A command-line tool (and python library) to extract sqlite db from excel files
Home-page: https://github.com/fomuon/excel-export
Author: Lee,Yongkyu
Author-email: fomuon@gmail.com
License: BSD
Keywords: excel-export,excel,sqlite
Platform: UNKNOWN
